rcpyconfig/Configuration.py
rcpyconfig/__init__.py
rcpyconfig-1.0.0.data/data/Pipfile
rcpyconfig-1.0.0.dist-info/LICENSE
rcpyconfig-1.0.0.dist-info/METADATA
rcpyconfig-1.0.0.dist-info/WHEEL
rcpyconfig-1.0.0.dist-info/top_level.txt
rcpyconfig-1.0.0.dist-info/RECORD
